cubie/CUDAFactory.py
cubie/__init__.py
cubie/_utils.py
cubie/buffer_registry.py
cubie/cuda_simsafe.py
cubie/time_logger.py
cubie/batchsolving/BatchGridBuilder.py
cubie/batchsolving/BatchSolverConfig.py
cubie/batchsolving/BatchSolverKernel.py
cubie/batchsolving/SystemInterface.py
cubie/batchsolving/__init__.py
cubie/batchsolving/_utils.py
cubie/batchsolving/solver.py
cubie/batchsolving/solveresult.py
cubie/batchsolving/arrays/BaseArrayManager.py
cubie/batchsolving/arrays/BatchInputArrays.py
cubie/batchsolving/arrays/BatchOutputArrays.py
cubie/batchsolving/arrays/__init__.py
cubie/integrators/IntegratorRunSettings.py
cubie/integrators/SingleIntegratorRun.py
cubie/integrators/SingleIntegratorRunCore.py
cubie/integrators/__init__.py
cubie/integrators/array_interpolator.py
cubie/integrators/algorithms/__init__.py
cubie/integrators/algorithms/backwards_euler.py
cubie/integrators/algorithms/backwards_euler_predict_correct.py
cubie/integrators/algorithms/base_algorithm_step.py
cubie/integrators/algorithms/crank_nicolson.py
cubie/integrators/algorithms/explicit_euler.py
cubie/integrators/algorithms/generic_dirk.py
cubie/integrators/algorithms/generic_dirk_tableaus.py
cubie/integrators/algorithms/generic_erk.py
cubie/integrators/algorithms/generic_erk_tableaus.py
cubie/integrators/algorithms/generic_firk.py
cubie/integrators/algorithms/generic_firk_tableaus.py
cubie/integrators/algorithms/generic_rosenbrock_w.py
cubie/integrators/algorithms/generic_rosenbrockw_tableaus.py
cubie/integrators/algorithms/ode_explicitstep.py
cubie/integrators/algorithms/ode_implicitstep.py
cubie/integrators/loops/__init__.py
cubie/integrators/loops/ode_loop.py
cubie/integrators/loops/ode_loop_config.py
cubie/integrators/matrix_free_solvers/__init__.py
cubie/integrators/matrix_free_solvers/linear_solver.py
cubie/integrators/matrix_free_solvers/newton_krylov.py
cubie/integrators/step_control/__init__.py
cubie/integrators/step_control/adaptive_I_controller.py
cubie-0.0.6.dist-info/licenses/src/LICENSE
cubie-0.0.6.dist-info/METADATA
cubie-0.0.6.dist-info/WHEEL
cubie-0.0.6.dist-info/top_level.txt
cubie-0.0.6.dist-info/RECORD
