Metadata-Version: 2.4
Name: cubie
Version: 0.0.6
Summary: CUDA Batch Integration Engine.
Author: Chris Cameron
License-Expression: MIT
Project-URL: Homepage, https://github.com/ccam80/cubie.git
Project-URL: Issues, https://github.com/ccam80/cubie/issues
Requires-Python: >=3.9
License-File: src/LICENSE
Requires-Dist: numpy==1.26.4
Requires-Dist: numba
Requires-Dist: numba-cuda[cu12]
Requires-Dist: attrs
Requires-Dist: sympy>=1.13.0
Requires-Dist: cellmlmanip
Provides-Extra: dev
Requires-Dist: pytest; extra == "dev"
Requires-Dist: pytest-cov; extra == "dev"
Requires-Dist: pytest-durations; extra == "dev"
Requires-Dist: pytest-json-report; extra == "dev"
Requires-Dist: flake8; extra == "dev"
Requires-Dist: ruff; extra == "dev"
Requires-Dist: cupy-cuda12x; extra == "dev"
Requires-Dist: pandas; extra == "dev"
Requires-Dist: matplotlib; extra == "dev"
Requires-Dist: scipy; extra == "dev"
Provides-Extra: cupy
Requires-Dist: cupy-cuda12x; extra == "cupy"
Provides-Extra: optional
Requires-Dist: pandas; extra == "optional"
Requires-Dist: matplotlib; extra == "optional"
Dynamic: license-file
